boolenv/__init__.py
boolenv/__main__.py
boolenv-1.0.4.dist-info/METADATA
boolenv-1.0.4.dist-info/WHEEL
boolenv-1.0.4.dist-info/top_level.txt
boolenv-1.0.4.dist-info/RECORD
