Metadata-Version: 2.1
Name: boolenv
Version: 1.0.4
Summary: Read Boolean value from environment variable
Home-page: https://github.com/ondrejsika/python-boolenv
Author: Ondrej Sika
Author-email: ondrej@ondrejsika.com
License: UNKNOWN
Platform: UNKNOWN
